LICENSE
README.md
setup.py
claripy/__init__.py
claripy/tests/__init__.py
claripy_sdk.egg-info/PKG-INFO
claripy_sdk.egg-info/SOURCES.txt
claripy_sdk.egg-info/dependency_links.txt
claripy_sdk.egg-info/requires.txt
claripy_sdk.egg-info/top_level.txt