Metadata-Version: 2.1
Name: claripy-sdk
Version: 1.0.3
Summary: Python SDK for use with Clarity.io sensors
Home-page: https://github.com/rogers-obrien-rad/clarity-python-sdk
Author-email: hfritz@r-o.com
License-File: LICENSE
